plone.app.contentmenu-3.0.8-py3.13-nspkg.pth
plone/app/contentmenu/__init__.py
plone/app/contentmenu/configure.zcml
plone/app/contentmenu/contentmenu.pt
plone/app/contentmenu/displayviewsmenu.py
plone/app/contentmenu/interfaces.py
plone/app/contentmenu/menu.py
plone/app/contentmenu/testing.py
plone/app/contentmenu/view.py
plone/app/contentmenu/tests/__init__.py
plone/app/contentmenu/tests/test_menu.py
plone_app_contentmenu-3.0.8.dist-info/METADATA
plone_app_contentmenu-3.0.8.dist-info/WHEEL
plone_app_contentmenu-3.0.8.dist-info/namespace_packages.txt
plone_app_contentmenu-3.0.8.dist-info/top_level.txt
plone_app_contentmenu-3.0.8.dist-info/RECORD
